Assignment-3/G4R_2005330_200562_200856_A3/A3Q1_seq_detect.v
module seq_detect(clk,in,out);
    input clk;
    input in;
    output reg out;
    parameter S0=2'b00,S1=2'b01,S2=2'b10,S3=2'b11;
    reg [1:0] state;
    always @(posedge clk or in) begin
        case (state)
            S0: begin
                if(in) begin
                    out=1'b0;
                    state<=S1;
                end
                else begin
                    out=1'b0;
                end
            end
            S1: begin
                if(~in) begin
                    out=1'b0;
                    state<=S2;
                end
                else begin
                    out=1'b0;
                end
            end
            S2: begin
                if(in) begin
                    out=1'b0;
                    state<=S3;
                end
                else begin
                    out=1'b0;
                    state<=S0;
                end
            end
            S3: begin
                if(in) begin
                    out=1'b0;
                    state<=S1;
                end
                else begin
                    out=1'b1;
                    state<=S2;
                end
            end
            default: begin
                out=1'b0;
                state<=S0;
            end
            endcase
    end
endmodule

Assignment-3/G4R_2005330_200562_200856_A3/A3Q1_seq_detect_tb.v
`timescale 1ps/1ps
`include "A3Q1_seq_detect.v"

module testbench;

    reg clk=0;
    reg in;
    wire out;

    seq_detect uut(clk,in,out);

    always #5 clk=~clk;
    initial begin
        $dumpfile("A3Q1_seq_detect.vcd");
        $dumpvars(0,testbench);
        in=1;#5;
        $display("After processing one bit from input stream out = %b",out);
        in=1;#5;
        $display("After processing one bit from input stream out = %b",out);
        in=0;#5;
        $display("After processing one bit from input stream out = %b",out);
        in=1;#5;
        $display("After processing one bit from input stream out = %b",out);
        in=0;#5;
        $display("After processing one bit from input stream out = %b",out);
        in=1;#5;
        $display("After processing one bit from input stream out = %b",out);
        in=0;#5;
        $display("After processing one bit from input stream out = %b",out);
        in=1;#5;
        $display("After processing one bit from input stream out = %b",out);
        in=0;#5;
        $display("After processing one bit from input stream out = %b",out);
        in=1;#5;
        $display("After processing one bit from input stream out = %b",out);
        in=1;#5;
        $display("After processing one bit from input stream out = %b",out);
        $display("end of test and open gtkwave");
        $finish;
    end
endmodule

Assignment-3/G4R_2005330_200562_200856_A3/A3Q1_seq_detect.vcd
$date
	Thu Feb 17 23:54:23 2022
$end
$version
	Icarus Verilog
$end
$timescale
	1ps
$end
$scope module testbench $end
$var wire 1 ! out $end
$var reg 1 " clk $end
$var reg 1 # in $end
$scope module uut $end
$var wire 1 " clk $end
$var wire 1 # in $end
$var reg 1 ! out $end
$var reg 2 $ state [1:0] $end
$upscope $end
$upscope $end
$enddefinitions $end
#0
$dumpvars
b0 $
1#
0"
0!
$end
#5
b1 $
1"
#10
b10 $
0#
0"
#15
b11 $
1#
1"
#20
b10 $
1!
0#
0"
#25
b11 $
0!
1#
1"
#30
b10 $
1!
0#
0"
#35
b11 $
0!
1#
1"
#40
b10 $
1!
0#
0"
#45
b11 $
0!
1#
1"
#50
0"
#55
b1 $
1"
