Assignment-1/ques3/_3to8.v
module _2to4 (a,en,d);
input [1:0] a;
input en;
output [3:0] d;
assign d[0]=en & ~a[0] & ~a[1];
assign d[1]=en & a[0] & ~a[1];
assign d[2]=en & ~a[0] & a[1];
assign d[3]=en & a[0] & a[1];
endmodule

module _3to8 (a,en,d);
input [2:0] a;
input en;
output [7:0] d;
wire [7:0] w;
_2to4 c(.a(a[1:0]),.en(a[2]),.d(w[7:4]));
_2to4 e(.a(a[1:0]),.en(~a[2]),.d(w[3:0]));

assign d=w;

endmodule

_3to8_tb.v
`timescale 1ns/1ns
`include "_3to8.v"

module _3to8_tb;

reg [2:0] a;
wire [7:0] d;
reg en;

_3to8 uut(a,en,d);

initial begin
    $dumpfile("_3to8_tb.vcd");
    $dumpvars(0,_3to8_tb);
    en=1;
    a=3'b000;#20;
    a=3'b001;#20;
    a=3'b010;#20;
    a=3'b011;#20;
    a=3'b100;#20;
    a=3'b101;#20;
    a=3'b110;#20;
    a=3'b111;#20;
    $display("end of test");
end
endmodule

_3to8_tb.vcd
$date
	Tue Jan 18 16:15:06 2022
$end
$version
	Icarus Verilog
$end
$timescale
	1ns
$end
$scope module _3to8_tb $end
$var wire 8 ! d [7:0] $end
$var reg 3 " a [2:0] $end
$var reg 1 # en $end
$scope module uut $end
$var wire 3 $ a [2:0] $end
$var wire 8 % d [7:0] $end
$var wire 1 # en $end
$var wire 8 & w [7:0] $end
$scope module c $end
$var wire 2 ' a [1:0] $end
$var wire 1 ( en $end
$var wire 4 ) d [3:0] $end
$upscope $end
$scope module e $end
$var wire 2 * a [1:0] $end
$var wire 1 + en $end
$var wire 4 , d [3:0] $end
$upscope $end
$upscope $end
$upscope $end
$enddefinitions $end
#0
$dumpvars
b1 ,
1+
b0 *
b0 )
0(
b0 '
b1 &
b1 %
b0 $
1#
b0 "
b1 !
$end
#20
b10 !
b10 %
b10 &
b10 ,
b1 '
b1 *
b1 "
b1 $
#40
b100 !
b100 %
b100 &
b100 ,
b10 '
b10 *
b10 "
b10 $
#60
b1000 !
b1000 %
b1000 &
b1000 ,
b11 '
b11 *
b11 "
b11 $
#80
b1 )
b10000 !
b10000 %
b10000 &
b0 ,
0+
b0 '
1(
b0 *
b100 "
b100 $
#100
b100000 !
b100000 %
b100000 &
b10 )
b1 '
b1 *
b101 "
b101 $
#120
b1000000 !
b1000000 %
b1000000 &
b100 )
b10 '
b10 *
b110 "
b110 $
#140
b10000000 !
b10000000 %
b10000000 &
b1000 )
b11 '
b11 *
b111 "
b111 $
