Assignment-2/G4R_200530_200562_200856_A2/A2Q1_look_ahead_adder.v
module CLAA(sum,A,B);
    input[7:0] A,B;
    output [7:0] sum;

    wire [7:0] P,Q;  //wires for storing the generator and 
    assign P=A&B;    //propogator values
    assign Q=A^B;
    reg[8:0] carry;  // register to store the carry values of each bit
    integer i;
    always @(*) begin
        carry[0]=0;
        for(i = 0; i < 8; i = i+1) begin
            carry[i+1] = P[i] | (Q[i] & carry[i]); //implenting the formula for
        end                                        //each carry bit
    end
    assign sum=(Q)^carry;     //final step for sum registers (A^B)^Carry
endmodule

Assignment-2/G4R_200530_200562_200856_A2/A2Q1_look_ahead_adder_tb.v
`timescale 1ps/1ps
`include "A2Q1_look_ahead_adder.v"

module test_bench();
    reg[7:0] A,B;   //input regtesisters
    wire[7:0] S;    //output sum register
    
    CLAA claa1(S,A,B);
    initial begin
        $dumpfile("A2Q1_look_ahead_adder_tb.vcd");
        $dumpvars(0,test_bench);
        A = 8'd0;
        B = 8'd0;
       
        #5; A = 1; B = 10 ;      // test cases
        #5; A = 5; B = 15 ;     
        #5; A = 7; B =  20;
        #5; A = 10; B = 30 ;
        #5; A = 15; B = 40 ;
        #5; A = 20; B = 50 ;
        #5; A = 25; B = 60 ;
        #5; A = 26; B = 70 ;
        #5; A = 31; B = 80 ;
        #5; A = 34; B = 90 ;
        #5; A = 37; B = 100 ;
        #5; A = 40; B = 110 ;
        #5; A = 50; B = 120 ;
        #5; A = 53; B = 130 ;
        #5; A = 65; B = 140 ;
        #5; A = 80; B = 150 ;
        #5; A = 100; B =  155;
        #5; A = 100; B = 200;
        #5;
        $finish;
    end
    initial begin
        $monitor("1st Input = %d , 2nd input = %d, Sum of inputs = %d",A,B,S); //input in terminal
    end                                                                        //and gtkwave

endmodule

Assignment-2/G4R_200530_200562_200856_A2/A2Q1_look_ahead_adder_tb.vcd
$date
	Sun Feb  6 23:49:45 2022
$end
$version
	Icarus Verilog
$end
$timescale
	1ps
$end
$scope module test_bench $end
$var wire 8 ! S [7:0] $end
$var reg 8 " A [7:0] $end
$var reg 8 # B [7:0] $end
$scope module claa1 $end
$var wire 8 $ A [7:0] $end
$var wire 8 % B [7:0] $end
$var wire 8 & P [7:0] $end
$var wire 8 ' Q [7:0] $end
$var wire 8 ( sum [7:0] $end
$var reg 9 ) carry [8:0] $end
$var integer 32 * i [31:0] $end
$upscope $end
$upscope $end
$enddefinitions $end
#0
$dumpvars
b1000 *
b0 )
b0 (
b0 '
b0 &
b0 %
b0 $
b0 #
b0 "
b0 !
$end
#5
b1011 !
b1011 (
b1000 *
b1011 '
b1010 #
b1010 %
b1 "
b1 $
#10
b10100 !
b10100 (
b11110 )
b1000 *
b101 &
b1010 '
b1111 #
b1111 %
b101 "
b101 $
#15
b11011 !
b11011 (
b1000 )
b1000 *
b100 &
b10011 '
b10100 #
b10100 %
b111 "
b111 $
#20
b101000 !
b101000 (
b111100 )
b1000 *
b1010 &
b10100 '
b11110 #
b11110 %
b1010 "
b1010 $
#25
b110111 !
b110111 (
b10000 )
b1000 *
b1000 &
b100111 '
b101000 #
b101000 %
b1111 "
b1111 $
#30
b1000110 !
b1000110 (
b1100000 )
b1000 *
b10000 &
b100110 '
b110010 #
b110010 %
b10100 "
b10100 $
#35
b1010101 !
b1010101 (
b1110000 )
b1000 *
b11000 &
b100101 '
b111100 #
b111100 %
b11001 "
b11001 $
#40
b1100000 !
b1100000 (
b111100 )
b1000 *
b10 &
b1011100 '
b1000110 #
b1000110 %
b11010 "
b11010 $
#45
b1101111 !
b1101111 (
b100000 )
b1000 *
b10000 &
b1001111 '
b1010000 #
b1010000 %
b11111 "
b11111 $
#50
b1111100 !
b1111100 (
b100 )
b1000 *
b10 &
b1111000 '
b1011010 #
b1011010 %
b100010 "
b100010 $
#55
b10001001 !
b10001001 (
b11001000 )
b1000 *
b100100 &
b1000001 '
b1100100 #
b1100100 %
b100101 "
b100101 $
#60
b10010110 !
b10010110 (
b11010000 )
b1000 *
b101000 &
b1000110 '
b1101110 #
b1101110 %
b101000 "
b101000 $
#65
b10101010 !
b10101010 (
b11100000 )
b1000 *
b110000 &
b1001010 '
b1111000 #
b1111000 %
b110010 "
b110010 $
#70
b10110111 !
b10110111 (
b0 )
b1000 *
b0 &
b10110111 '
b10000010 #
b10000010 %
b110101 "
b110101 $
#75
b11001101 !
b11001101 (
b1000 *
b11001101 '
b10001100 #
b10001100 %
b1000001 "
b1000001 $
#80
b11100110 !
b11100110 (
b100000 )
b1000 *
b10000 &
b11000110 '
b10010110 #
b10010110 %
b1010000 "
b1010000 $
#85
b11111111 !
b11111111 (
b0 )
b1000 *
b0 &
b11111111 '
b10011011 #
b10011011 %
b1100100 "
b1100100 $
#90
b101100 !
b101100 (
b110000000 )
b1000 *
b1000000 &
b10101100 '
b11001000 #
b11001000 %
