Assignment-1/3to8_decoder/2to4_decoder.v
module _2to4 (a,en,d);
input [1:0] a;
input en;
output [3:0] d;
assign d[0]=en & ~a[0] & ~a[1];
assign d[1]=en & a[0] & ~a[1];
assign d[2]=en & ~a[0] & a[1];
assign d[3]=en & a[0] & a[1];
endmodule

Assignment-1/3to8_decoder/3to8_decoder.v
`include "2to4_decoder.v"
module _3to8 (a,d);
input [2:0] a;

output [7:0] d;
wire [7:0] w;
_2to4 c(.a(a[1:0]),.en(a[2]),.d(w[7:4]));
_2to4 e(.a(a[1:0]),.en(~a[2]),.d(w[3:0]));

assign d=w;

endmodule

Assignment-1/3to8_decoder/3to8_decoder_tb.v
`timescale 1ns/1ns
`include "3to8_decoder.v"

module _3to8_tb;

reg [2:0] a;
wire [7:0] d;

_3to8 uut(a,d);

initial begin
    $dumpfile("3to8_deocder_tb.vcd");
    $dumpvars(0,_3to8_tb);
    a=3'b000;#5;
    a=3'b001;#5;
    a=3'b010;#5;
    a=3'b011;#5;
    a=3'b100;#5;
    a=3'b101;#5;
    a=3'b110;#5;
    a=3'b111;#5;
    $display("end of test");
end
initial begin
    $monitor("Input = %b , gives output = %b",a,d);
end
endmodule

Assignment-1/3to8_decoder/3to8_deocder_tb.vcd
$date
	Sun Jan 23 19:01:58 2022
$end
$version
	Icarus Verilog
$end
$timescale
	1ns
$end
$scope module _3to8_tb $end
$var wire 8 ! d [7:0] $end
$var reg 3 " a [2:0] $end
$scope module uut $end
$var wire 3 # a [2:0] $end
$var wire 8 $ d [7:0] $end
$var wire 8 % w [7:0] $end
$scope module c $end
$var wire 2 & a [1:0] $end
$var wire 1 ' en $end
$var wire 4 ( d [3:0] $end
$upscope $end
$scope module e $end
$var wire 2 ) a [1:0] $end
$var wire 1 * en $end
$var wire 4 + d [3:0] $end
$upscope $end
$upscope $end
$upscope $end
$enddefinitions $end
#0
$dumpvars
b1 +
1*
b0 )
b0 (
0'
b0 &
b1 %
b1 $
b0 #
b0 "
b1 !
$end
#5
b10 !
b10 $
b10 %
b10 +
b1 &
b1 )
b1 "
b1 #
#10
b100 !
b100 $
b100 %
b100 +
b10 &
b10 )
b10 "
b10 #
#15
b1000 !
b1000 $
b1000 %
b1000 +
b11 &
b11 )
b11 "
b11 #
#20
b1 (
b10000 !
b10000 $
b10000 %
b0 +
0*
b0 &
1'
b0 )
b100 "
b100 #
#25
b100000 !
b100000 $
b100000 %
b10 (
b1 &
b1 )
b101 "
b101 #
#30
b1000000 !
b1000000 $
b1000000 %
b100 (
b10 &
b10 )
b110 "
b110 #
#35
b10000000 !
b10000000 $
b10000000 %
b1000 (
b11 &
b11 )
b111 "
b111 #
