Assignment-4/A4Q2_oneBit.v
module onebit(a,b,cin,opcode,sum,cout);
input a,b,cin,opcode;
output sum,cout;
assign sum=a^(b^opcode)^cin;
assign cout=(a&cin)|(a&(b^opcode))|((b^opcode)&cin);
endmodule

Assignment-4/A4Q2_eightBit.v
`include "A4Q2_oneBit.v"
module eightbit(a,b,opcode,res,cout,flag); //flag to check whether overflow occured or not? true if occured
input [7:0] a,b;
input opcode;
output [7:0] res;
output wire cout, flag;
wire [7:0] carry;
wire cin;
assign cin = opcode;

onebit S0(a[0],b[0],cin,opcode,res[0],carry[0]);
onebit S1(a[1],b[1],carry[0],opcode,res[1],carry[1]);
onebit S2(a[2],b[2],carry[1],opcode,res[2],carry[2]);
onebit S3(a[3],b[3],carry[2],opcode,res[3],carry[3]);
onebit S4(a[4],b[4],carry[3],opcode,res[4],carry[4]);
onebit S5(a[5],b[5],carry[4],opcode,res[5],carry[5]);
onebit S6(a[6],b[6],carry[5],opcode,res[6],carry[6]);
onebit S7(a[7],b[7],carry[6],opcode,res[7],carry[7]);
assign flag = carry[6]^carry[7];
assign cout = carry[7];
endmodule

Assignment-4/A4Q2_eightBit_tb.v
`timescale 1ns/1ns
`include "A4Q2_eightBit.v"

module test_bench();

reg [7:0] A,B;
reg opcode;
wire [7:0] res;
wire cout, flag;

eightbit ok(A,B,opcode,res,cout,flag);

/* always @(A or B or opcode) begin
    if(opcode == 1'b0) $display("Addition of two inputs is =");
    else $display("Substraction of two inputs is =");
    if(flag == 1'b1) begin
        $display("Overflow Occured while evaluating");
    end
    else if(res[7] == 1'b1) $display("-%d",{1'b0, (~res[6:0] + 1'b1)});
    else $display("%d",res);
    $display("\n");
    if(A[7] == 1'b1) begin
        //A = {A[7], (~A[6:0] + 1'b1)};
        $display("1st input = -%d", {1'b0, (~A[6:0] + 1'b1)});

    end 
    else $display("1st input = %d", A);

    if(B[7] == 1'b1) begin
        //A = {A[7], (~A[6:0] + 1'b1)};
        $display("2nd input = -%d", {1'b0, (~B[6:0] + 1'b1)});
    end 
    else $display("2nd input = %d", B); 
end */
always #5 begin
    if(flag == 1'b1) begin
        if(res[7] == 1'b1) begin
            if(A[7] == 1'b1) begin 
                if(B[7] == 1'b1) begin
                    if(opcode == 1'b1) $display("(-%d) - (-%d) = -%d  *** Overflow Occured ",{1'b0, (~A[6:0] + 1'b1)},{1'b0, (~B[6:0] + 1'b1)},{1'b0, (~res[6:0] + 1'b1)});
                    else $display("(-%d) + (-%d) = -%d  *** Overflow Occured ",{1'b0, (~A[6:0] + 1'b1)},{1'b0, (~B[6:0] + 1'b1)},{1'b0, (~res[6:0] + 1'b1)});
                end
                else begin
                    if(opcode == 1'b1) $display("(-%d) - (%d) = -%d  *** Overflow Occured ",{1'b0, (~A[6:0] + 1'b1)},B,{1'b0, (~res[6:0] + 1'b1)});
                    else $display("(-%d) + (%d) = -%d  *** Overflow Occured ",{1'b0, (~A[6:0] + 1'b1)},B,{1'b0, (~res[6:0] + 1'b1)});
                end
            end
            else begin
                if(B[7] == 1'b1) begin
                    if(opcode == 1'b1) $display("(%d) - (-%d) = -%d  *** Overflow Occured ",A,{1'b0, (~B[6:0] + 1'b1)},{1'b0, (~res[6:0] + 1'b1)});
                    else $display("(%d) + (-%d) = -%d  *** Overflow Occured ",A,{1'b0, (~B[6:0] + 1'b1)},{1'b0, (~res[6:0] + 1'b1)});
                end
                else begin
                    if(opcode == 1'b1) $display("(%d) - (%d) = -%d  *** Overflow Occured ",A,B,{1'b0, (~res[6:0] + 1'b1)});
                    else $display("(%d) + (%d) = -%d  *** Overflow Occured ",A,B,{1'b0, (~res[6:0] + 1'b1)});
                end
            end
        end
        else begin
            if(A[7] == 1'b1) begin 
                if(B[7] == 1'b1) begin
                    if(opcode == 1'b1) $display("(-%d) - (-%d) = %d",{1'b0, (~A[6:0] + 1'b1)},{1'b0, (~B[6:0] + 1'b1)},res);
                    else $display("(-%d) + (-%d) = %d",{1'b0, (~A[6:0] + 1'b1)},{1'b0, (~B[6:0] + 1'b1)},res);
                end
                else begin
                    if(opcode == 1'b1) $display("(-%d) - (%d) = %d",{1'b0, (~A[6:0] + 1'b1)},B,res);
                    else $display("(-%d) + (%d) = %d",{1'b0, (~A[6:0] + 1'b1)},B,res);
                end
            end
            else begin
                if(B[7] == 1'b1) begin
                    if(opcode == 1'b1) $display("(%d) - (-%d) = %d",A,{1'b0, (~B[6:0] + 1'b1)},res);
                    else $display("(%d) + (-%d) = %d",A,{1'b0, (~B[6:0] + 1'b1)},res);
                end
                else begin
                    if(opcode == 1'b1) $display("(%d) - (%d) = %d",A,B,res);
                    else $display("(%d) + (%d) = %d",A,B,res);
                end
            end
        end
    end
    else begin
        if(res[7] == 1'b1) begin
            if(A[7] == 1'b1) begin 
                if(B[7] == 1'b1) begin
                    if(opcode == 1'b1) $display("(-%d) - (-%d) = -%d",{1'b0, (~A[6:0] + 1'b1)},{1'b0, (~B[6:0] + 1'b1)},{1'b0, (~res[6:0] + 1'b1)});
                    else $display("(-%d) + (-%d) = -%d",{1'b0, (~A[6:0] + 1'b1)},{1'b0, (~B[6:0] + 1'b1)},{1'b0, (~res[6:0] + 1'b1)});
                end
                else begin
                    if(opcode == 1'b1) $display("(-%d) - (%d) = -%d",{1'b0, (~A[6:0] + 1'b1)},B,{1'b0, (~res[6:0] + 1'b1)});
                    else $display("(-%d) + (%d) = -%d",{1'b0, (~A[6:0] + 1'b1)},B,{1'b0, (~res[6:0] + 1'b1)});
                end
            end
            else begin
                if(B[7] == 1'b1) begin
                    if(opcode == 1'b1) $display("(%d) - (-%d) = -%d",A,{1'b0, (~B[6:0] + 1'b1)},{1'b0, (~res[6:0] + 1'b1)});
                    else $display("(%d) + (-%d) = -%d",A,{1'b0, (~B[6:0] + 1'b1)},{1'b0, (~res[6:0] + 1'b1)});
                end
                else begin
                    if(opcode == 1'b1) $display("(%d) - (%d) = -%d",A,B,{1'b0, (~res[6:0] + 1'b1)});
                    else $display("(%d) + (%d) = -%d",A,B,{1'b0, (~res[6:0] + 1'b1)});
                end
            end
        end
        else begin
            if(A[7] == 1'b1) begin 
                if(B[7] == 1'b1) begin
                    if(opcode == 1'b1) $display("(-%d) - (-%d) = %d",{1'b0, (~A[6:0] + 1'b1)},{1'b0, (~B[6:0] + 1'b1)},res);
                    else $display("(-%d) + (-%d) = %d",{1'b0, (~A[6:0] + 1'b1)},{1'b0, (~B[6:0] + 1'b1)},res);
                end
                else begin
                    if(opcode == 1'b1) $display("(-%d) - (%d) = %d",{1'b0, (~A[6:0] + 1'b1)},B,res);
                    else $display("(-%d) + (%d) = %d",{1'b0, (~A[6:0] + 1'b1)},B,res);
                end
            end
            else begin
                if(B[7] == 1'b1) begin
                    if(opcode == 1'b1) $display("(%d) - (-%d) = %d",A,{1'b0, (~B[6:0] + 1'b1)},res);
                    else $display("(%d) + (-%d) = %d",A,{1'b0, (~B[6:0] + 1'b1)},res);
                end
                else begin
                    if(opcode == 1'b1) $display("(%d) - (%d) = %d",A,B,res);
                    else $display("(%d) + (%d) = %d",A,B,res);
                end
            end
        end

    end
end
initial begin
    $dumpfile("A4Q2_eightBit_tb.vcd");
    $dumpvars(0,test_bench);
    opcode=0;
    A = 50 ; B = 10 ; opcode = 1; #5
    
    A = 0 ; B = 0 ; opcode = 1; #5;
    A = 5 ; B = 15  ; opcode = 1; #5;
    A = 7 ; B = 20  ; opcode = 1; #5;
    A = 10; B = 30  ; opcode = 0; #5;
    A = 15; B = 40  ; opcode = 1; #5;
    A = 20; B = 50  ; opcode = 1; #5;
    A = 25; B = 60  ; opcode = 1; #5;
    A = 26; B = 70  ; opcode = 0; #5;
    A = 31; B = 80  ; opcode = 1; #5;
    A = 13; B = 90  ; opcode = 1; #5;
    A = 37; B = 100 ; opcode = 1; #5;
    A = 40; B = 110 ; opcode = 0; #5;
    A = 50; B = 120 ; opcode = 1; #5;
    A = 53; B = 130 ; opcode = 1; #5;
    A = 65; B = 140 ; opcode = 0; #5;
    A = 80; B = 150 ; opcode = 1; #5;
    A = 150; B = 1; opcode = 0; #5;
    A = 5; B = 10; opcode = 1; #5;
    $finish;
end


endmodule

Assignment-4/A4Q2_eightBit_tb.vcd
$date
	Fri Mar  4 09:59:24 2022
$end
$version
	Icarus Verilog
$end
$timescale
	1ns
$end
$scope module test_bench $end
$var wire 8 ! res [7:0] $end
$var wire 1 " flag $end
$var wire 1 # cout $end
$var reg 8 $ A [7:0] $end
$var reg 8 % B [7:0] $end
$var reg 1 & opcode $end
$scope module ok $end
$var wire 8 ' a [7:0] $end
$var wire 8 ( b [7:0] $end
$var wire 1 ) cin $end
$var wire 1 " flag $end
$var wire 1 & opcode $end
$var wire 8 * res [7:0] $end
$var wire 1 # cout $end
$var wire 8 + carry [7:0] $end
$scope module S0 $end
$var wire 1 , a $end
$var wire 1 - b $end
$var wire 1 ) cin $end
$var wire 1 . cout $end
$var wire 1 & opcode $end
$var wire 1 / sum $end
$upscope $end
$scope module S1 $end
$var wire 1 0 a $end
$var wire 1 1 b $end
$var wire 1 2 cin $end
$var wire 1 3 cout $end
$var wire 1 & opcode $end
$var wire 1 4 sum $end
$upscope $end
$scope module S2 $end
$var wire 1 5 a $end
$var wire 1 6 b $end
$var wire 1 7 cin $end
$var wire 1 8 cout $end
$var wire 1 & opcode $end
$var wire 1 9 sum $end
$upscope $end
$scope module S3 $end
$var wire 1 : a $end
$var wire 1 ; b $end
$var wire 1 < cin $end
$var wire 1 = cout $end
$var wire 1 & opcode $end
$var wire 1 > sum $end
$upscope $end
$scope module S4 $end
$var wire 1 ? a $end
$var wire 1 @ b $end
$var wire 1 A cin $end
$var wire 1 B cout $end
$var wire 1 & opcode $end
$var wire 1 C sum $end
$upscope $end
$scope module S5 $end
$var wire 1 D a $end
$var wire 1 E b $end
$var wire 1 F cin $end
$var wire 1 G cout $end
$var wire 1 & opcode $end
$var wire 1 H sum $end
$upscope $end
$scope module S6 $end
$var wire 1 I a $end
$var wire 1 J b $end
$var wire 1 K cin $end
$var wire 1 L cout $end
$var wire 1 & opcode $end
$var wire 1 M sum $end
$upscope $end
$scope module S7 $end
$var wire 1 N a $end
$var wire 1 O b $end
$var wire 1 P cin $end
$var wire 1 Q cout $end
$var wire 1 & opcode $end
$var wire 1 R sum $end
$upscope $end
$upscope $end
$upscope $end
$enddefinitions $end
#0
$dumpvars
0R
1Q
1P
0O
0N
0M
1L
1K
0J
0I
1H
1G
1F
0E
1D
0C
1B
0A
0@
1?
1>
0=
1<
1;
0:
09
18
17
06
05
04
13
12
11
10
0/
1.
0-
0,
b11110111 +
b101000 *
1)
b1010 (
b110010 '
1&
b1010 %
b110010 $
1#
0"
b101000 !
$end
#5
1#
1Q
0"
0R
1P
1L
0M
1K
1G
1A
1F
0>
1=
b11111111 +
1B
04
0C
b0 !
b0 *
0H
01
0;
00
0?
0D
b0 %
b0 (
b0 $
b0 '
#10
0#
0Q
0"
1R
0P
0L
1M
0K
0G
0<
1H
08
0F
0B
1C
07
0A
14
03
0>
b1 +
0=
0/
b11110110 !
b11110110 *
19
1-
11
16
1;
1,
15
b1111 %
b1111 (
b101 $
b101 '
#15
1A
1=
1<
18
09
17
1/
0>
1C
b1111 +
13
b11110011 !
b11110011 *
14
0-
01
0;
1@
10
b10100 %
b10100 (
b111 $
b111 '
#20
04
02
1F
0.
0C
b11110 +
1B
1H
0M
0R
1>
b101000 !
b101000 *
0/
11
1;
0,
05
1:
0)
0&
b11110 %
b11110 (
b1010 $
b1010 '
#25
14
12
0>
1M
1R
19
b11111 +
1.
b11100111 !
b11100111 *
1/
01
06
0@
1E
1,
15
1)
1&
b101000 %
b101000 (
b1111 $
b1111 '
#30
09
07
b11101 +
03
0/
14
0>
b11100010 !
b11100010 *
0C
11
0;
1@
0,
00
0:
1?
b110010 %
b110010 (
b10100 $
b10100 '
#35
0H
0F
0B
1C
0A
0=
17
0<
04
13
b11 +
08
1/
19
b11011101 !
b11011101 *
1>
01
16
1;
1,
05
1:
b111100 %
b111100 (
b11001 $
b11001 '
#40
1H
1F
1B
0C
1A
1=
0>
02
1<
0.
09
b11110 +
18
0R
04
b1100000 !
b1100000 *
0/
11
0;
0@
0E
1J
0,
10
0)
0&
b1000110 %
b1000110 (
b11010 $
b11010 '
#45
14
1K
12
1>
0H
1G
1M
1R
19
b111111 +
1.
b11001111 !
b11001111 *
1/
01
06
1@
1,
15
1)
1&
b1010000 %
b1010000 (
b11111 $
b11111 '
#50
0M
0K
0G
09
1H
07
0F
0>
03
b1101 +
0B
14
b10110011 !
b10110011 *
1C
11
1;
00
0?
b1011010 %
b1011010 (
b1101 $
b1101 '
#55
1A
1=
1<
1M
17
18
1F
1K
04
13
09
0C
1B
b111111 +
1G
0>
b11000001 !
b11000001 *
0H
01
16
0;
0@
1E
0:
1D
b1100100 %
b1100100 (
b100101 $
b100101 '
#60
0<
08
19
07
03
14
1"
02
0F
1P
0.
1C
0B
0H
0M
b1101000 +
1L
1R
0>
b10010110 !
b10010110 *
0/
11
1;
0,
05
1:
0)
0&
b1101110 %
b1101110 (
b101000 $
b101000 '
#65
1>
0"
1<
18
09
0K
17
0A
0F
0G
0P
0#
13
0=
0B
12
1H
0M
0L
1R
0Q
14
1C
b111 +
1.
b10111010 !
b10111010 *
0/
01
06
1@
10
0:
1?
1)
1&
b1111000 %
b1111000 (
b110010 $
b110010 '
#70
1"
1P
1L
1F
1K
1A
1B
1G
07
0>
1=
1C
1H
0M
1R
b1111101 +
03
1/
14
b10110011 !
b10110011 *
09
11
0;
0@
0E
0J
1O
1,
00
15
b10000010 %
b10000010 (
b110101 $
b110101 '
#75
0C
0P
0A
0L
0=
1>
04
0H
1M
0"
0<
02
0F
0K
0#
08
0.
0B
0G
1R
b0 +
0Q
19
b11001101 !
b11001101 *
1/
01
16
1;
05
0?
0D
1I
0)
0&
b10001100 %
b10001100 (
b1000001 $
b1000001 '
#80
1"
1P
14
1L
12
09
1H
0M
1R
1C
b1000001 +
1.
b10111010 !
b10111010 *
0/
11
0;
1@
0,
1?
1)
1&
b10010110 %
b10010110 (
b1010000 $
b1010000 '
#85
0"
0<
08
07
0P
0#
03
0L
0Q
02
0>
0H
14
19
1R
b0 +
0.
b10010111 !
b10010111 *
1/
1-
01
06
0@
0O
10
15
0I
1N
0)
0&
b1 %
b1 (
b10010110 $
b10010110 '
#90
1>
1<
18
12
09
1H
1M
14
b101 +
1.
b11111011 !
b11111011 *
1/
0-
11
1;
1,
00
0?
0N
1)
1&
b1010 %
b1010 (
b101 $
b101 '
