Assignment-5/G4R_200530_200562_200856_A5/Assignment-5/A5Q1_gcd.v
module gcd(A_in,B_in,hcf);
parameter len = 8;
input [len-1:0] A_in,B_in;
reg [len-1:0] A,B;
output reg [len-1:0] hcf;
integer count;
always @(A_in,B_in) begin
    A=A_in;
    B=B_in;
    count=0;
    while (A!=B) begin
        if(A[0]==0 && B[0]==0) begin
            A=A>>1;
            B=B>>1;
            count=count+1;
        end
        else if(A[0]==1 && B[0]==0) begin
            B=B>>1;
        end
        else if(A[0]==0 && B[0]==1) begin
            A=A>>1;
        end
        else if(A>=B) begin
            A=(A-B)>>1;
        end
        else begin
            B=(B-A)>>1;
        end
    end
    while (count>0) begin
        A=A<<1;
        count=count-1;
    end
    hcf=A;
end

endmodule

Assignment-5/A5Q1_gcd_tb.v
`timescale 1ns/1ns
`include "A5Q1_gcd.v"

module gcd_tb;

reg [7:0] A_in;
reg [7:0] B_in;
wire [7:0] hcf;


gcd uut(A_in,B_in,hcf);

//ensure that B_in!=0_in and A_in!=0
initial begin
    $dumpfile("A5Q1_gcd_tb.vcd");
    $dumpvars(0,gcd_tb);

  
    A_in=8'd64;B_in=8'd32;#5;
    A_in=8'd13;B_in=8'd26;#5;
    A_in=8'd49;B_in=8'd33;#5;
    A_in=8'd31;B_in=8'd148;#5;
    A_in=8'd74;B_in=8'd68;#5;
    A_in=8'd177;B_in=8'd142;#5;
    A_in=8'd180;B_in=8'd84;#5;
    A_in=8'd145;B_in=8'd133;#5;
    A_in=8'd67;B_in=8'd128;#5;
    A_in=8'd37;B_in=8'd59;#5;
    A_in=8'd56;B_in=8'd31;#5;
    A_in=8'd100;B_in=8'd70;#5;
    A_in=8'd174;B_in=8'd58;#5;
    A_in=8'd62;B_in=8'd161;#5;
    $finish;
end

initial begin
    $monitor("hcf of %d and %d is :%d",A_in,B_in,hcf);
end

endmodule

Assignment-5/A5Q1_gcd_tb.vcd
$date
	Wed Mar 23 19:11:08 2022
$end
$version
	Icarus Verilog
$end
$timescale
	1ns
$end
$scope module gcd_tb $end
$var wire 8 ! hcf [7:0] $end
$var reg 8 " A_in [7:0] $end
$var reg 8 # B_in [7:0] $end
$scope module uut $end
$var wire 8 $ A_in [7:0] $end
$var wire 8 % B_in [7:0] $end
$var reg 8 & A [7:0] $end
$var reg 8 ' B [7:0] $end
$var reg 8 ( hcf [7:0] $end
$var integer 32 ) count [31:0] $end
$upscope $end
$upscope $end
$enddefinitions $end
#0
$dumpvars
b0 )
b100000 (
b1 '
b100000 &
b100000 %
b1000000 $
b100000 #
b1000000 "
b100000 !
$end
#5
b1101 !
b1101 (
b1101 '
b1101 &
b11010 #
b11010 %
b1101 "
b1101 $
#10
b1 !
b1 (
b1 '
b1 &
b100001 #
b100001 %
b110001 "
b110001 $
#15
b1 '
b1 &
b10010100 #
b10010100 %
b11111 "
b11111 $
#20
b10 !
b10 (
b0 )
b1 '
b10 &
b1000100 #
b1000100 %
b1001010 "
b1001010 $
#25
b1 !
b1 (
b1 '
b1 &
b10001110 #
b10001110 %
b10110001 "
b10110001 $
#30
b1100 !
b1100 (
b0 )
b11 '
b1100 &
b1010100 #
b1010100 %
b10110100 "
b10110100 $
#35
b1 !
b1 (
b1 '
b1 &
b10000101 #
b10000101 %
b10010001 "
b10010001 $
#40
b1 '
b1 &
b10000000 #
b10000000 %
b1000011 "
b1000011 $
#45
b1 '
b1 &
b111011 #
b111011 %
b100101 "
b100101 $
#50
b1 '
b1 &
b11111 #
b11111 %
b111000 "
b111000 $
#55
b1010 !
b1010 (
b0 )
b101 '
b1010 &
b1000110 #
b1000110 %
b1100100 "
b1100100 $
#60
b111010 !
b111010 (
b0 )
b11101 '
b111010 &
b111010 #
b111010 %
b10101110 "
b10101110 $
#65
b1 !
b1 (
b1 '
b1 &
b10100001 #
b10100001 %
b111110 "
b111110 $
