Assignment-3/G4R_2005330_200562_200856_A3/A3Q2_3_bit_odd_parity_generator.v
module fsm_3_bit_odd_parity_generator(clock,reset,in,x);
input clock,reset,in;
output reg x;

parameter  state_0=3'b000, 
        state_1=3'b001, 
        state_2=3'b010, 
        state_3=3'b011, 
        state_4=3'b100, 
        state_5=3'b101, 
        state_6=3'b110 ;

reg[2:0] current_state;
reg[2:0] next_state;

always @(negedge clock) begin
    if(reset==1'b1)
        current_state<=state_0;
    else
        current_state=next_state;
end

always @(in or negedge clock) begin
    case(current_state)
    state_0:begin
        if(~in) begin
            next_state=state_2; x=0;
        end
        else begin
            next_state=state_1; x=1;
        end
    end

    state_1:begin
        if(~in) begin
            next_state=state_3; x=0;
        end
        else begin
            next_state=state_4; x=1;
        end
    end

    state_2:begin
        if(~in)begin
            next_state=state_4; x=0;
        end
        else begin
            next_state=state_3; x=1;
        end
    end

    state_3:begin
        if(~in) begin
            next_state=state_5; x=0; 
        end
        else begin
            next_state=state_6; x=1;
        end
    end
    state_4:begin
        if(~in) begin
            next_state=state_6; x=0; 
        end
        else begin
            next_state=state_5; x=1;
        end
    end
    state_5:begin
        next_state=state_0; x=0;
    end
    state_6:begin
        next_state=state_0; x=1;
    end

    default:begin
        next_state=state_0;
    end
endcase 
end

endmodule

Assignment-3/A3Q2_3_bit_odd_parity_generator_tb.v
`timescale 1ns/1ns
`include "A3Q2_3_bit_odd_parity_generator.v"

module testbench();
reg clock,reset,in;
wire x;
fsm_3_bit_odd_parity_generator f2(clock,reset,in,x);
always #0.5 clock=~clock;
initial begin
    $dumpfile("A3Q2_3_bit_odd_parity_generator_tb.vcd");
    $dumpvars(0,testbench);
    clock=0;
    reset=0;
    

    #1 in =1'b0;
    #1 in =1'b1;
    #1 in =1'b1;
    #5 in =1'b0;
    #1 in =1'b1;
    #1 in =1'b0;
    #5 in =1'b1;
    #1 in =1'b0;

    #1 in = 1'b0;
    #5 in = 1'b1;
    #1 in = 1'b0;
    #1 in = 1'b1;
    #5 in = 1'b1;
    #1 in = 1'b1;
    #1 in = 1'b1;
    #5 in = 1'b0;
    #1 in = 1'b1;
    #1 in = 1'b0;
    #5 in = 1'b1;
    #1 in = 1'b0;
    #1 in = 1'b1;
    
    #5;$finish;
end

always @(negedge clock) begin
    $display("output equals %b at time = ", x ,$time );
end

endmodule

Assignment-3/A3Q2_3_bit_odd_parity_generator_tb.vcd
$date
	Thu Feb 17 23:36:19 2022
$end
$version
	Icarus Verilog
$end
$timescale
	1ns
$end
$scope module testbench $end
$var wire 1 ! x $end
$var reg 1 " clock $end
$var reg 1 # in $end
$var reg 1 $ reset $end
$scope module f2 $end
$var wire 1 " clock $end
$var wire 1 # in $end
$var wire 1 $ reset $end
$var reg 3 % current_state [2:0] $end
$var reg 3 & next_state [2:0] $end
$var reg 1 ! x $end
$upscope $end
$upscope $end
$enddefinitions $end
#0
$dumpvars
b0 &
bx %
0$
x#
0"
x!
$end
#1
0#
1"
#2
1!
b1 &
b0 %
1#
0"
#3
1"
#4
b100 &
b1 %
0"
#5
1"
#6
b101 &
b100 %
0"
#7
1"
#8
b110 %
0!
b110 &
0"
0#
#9
1!
b0 &
1"
1#
#10
b0 %
0"
0#
#11
1"
#12
0!
b10 &
0"
#13
1"
#14
b100 &
b10 %
0"
#15
1!
b11 &
1"
1#
#16
b100 %
0!
b100 &
0"
0#
#17
1"
#18
b110 &
0"
#19
1"
#20
1!
b0 &
b110 %
0"
#21
1"
#22
b0 %
0"
1#
#23
0!
b10 &
1"
0#
#24
b1 %
1!
b1 &
0"
1#
#25
1"
#26
b100 &
0"
#27
1"
#28
b101 &
b100 %
0"
#29
1"
#30
0!
b0 &
b101 %
0"
#31
1"
#32
1!
b1 &
b0 %
0"
#33
1"
#34
b100 &
b1 %
0"
#35
1"
#36
b11 %
0!
b11 &
0"
0#
#37
1!
b110 &
1"
1#
#38
b101 %
0!
b101 &
0"
0#
#39
1"
#40
b0 &
0"
#41
1"
#42
b10 &
b0 %
0"
#43
1!
b1 &
1"
1#
#44
b10 %
0!
b10 &
0"
0#
#45
1!
b11 &
1"
1#
#46
b110 &
b11 %
0"
#47
1"
#48
b0 &
b110 %
0"
#49
1"
#50
b1 &
b0 %
0"
