Assignment-1/8_bit_carry_adder/1-bit_fullAdder.v
`timescale 1ps/1ps
module FA (sum, Cout, A, B, Cin);
    input A,B,Cin;
    output sum,Cout;
    wire A,B,Cin;
    wire Cout,sum;

    //for sum
    and g1(o1, nA, B, nCin);
    and g2(o2, A, nB, nCin);
    and g3(o3, nA, nB, Cin);
    and g4(o4, A, B, Cin);

    and g5(o5, nA, B, Cin);
    and g6(o6, A, nB, Cin);
    and g7(o7, A, B, nCin);

    not g8(nA, A);
    not g9(nB, B);
    not g10(nCin, Cin);

    or g11(sum, o1, o2, o3, o4);
    or g12(Cout, o5, o6, o7, o4);

endmodule

8_bit_carry_adder/RippleAdd.v
`timescale 1ps/1ps
`include "1-bit_fullAdder.v"
module Ripple_Add (S,Cout,A,B);
    input wire[7:0] A,B;
    output wire[7:0] S;
    output wire Cout;
    wire Cin = 0;
    wire c0,c1,c2,c3,c4,c5,c6;
    FA fa1(S[0], c0, A[0], B[0], Cin);
    FA fa2(S[1], c1, A[1], B[1], c0);
    FA fa3(S[2], c2, A[2], B[2], c1);
    FA fa4(S[3], c3, A[3], B[3], c2);
    FA fa5(S[4], c4, A[4], B[4], c3);
    FA fa6(S[5], c5, A[5], B[5], c4);
    FA fa7(S[6], c6, A[6], B[6], c5);
    FA fa8(S[7], Cout, A[7], B[7], c6);
endmodule

Assignment-1/8_bit_carry_adder/RippleAdd_tb.v
`timescale 1ps/1ps
`include "RippleAdd.v"

module tb();
    reg[7:0] A,B;
    wire[7:0] S;
    wire Cout;
    Ripple_Add ra(S, Cout, A, B);
    initial 
    begin
        $dumpfile("RippleAdd_tb.vcd");
        $dumpvars(0,tb);
        A = 8'd0;
        B = 8'd0;
       // #10 B = 8'b0001;
        #5; A = 1; 
        #5; B = 1;
        #10; A = 2;
        #10; B = 2;
        #10; B = 3;
        #10; A = 4;
        #10; A = 5;
        #10; B = 4;
        #10; B = 5;
        #10; A = 6;
        #10; B = 6;
        #10; A = 7;
        #10; B = 7;
        #10; A = 8;
        #10; B = 8;
        #10; A = 30;
        #10; B = 30;
        #10;
        $finish;

    end

endmodule

Assignment-1/8_bit_carry_adder/RippleAdd_tb.vcd
$date
	Tue Jan 18 11:17:32 2022
$end
$version
	Icarus Verilog
$end
$timescale
	1ps
$end
$scope module tb $end
$var wire 8 ! S [7:0] $end
$var wire 1 " Cout $end
$var reg 8 # A [7:0] $end
$var reg 8 $ B [7:0] $end
$scope module ra $end
$var wire 8 % A [7:0] $end
$var wire 8 & B [7:0] $end
$var wire 1 ' Cin $end
$var wire 1 ( c6 $end
$var wire 1 ) c5 $end
$var wire 1 * c4 $end
$var wire 1 + c3 $end
$var wire 1 , c2 $end
$var wire 1 - c1 $end
$var wire 1 . c0 $end
$var wire 8 / S [7:0] $end
$var wire 1 " Cout $end
$scope module fa1 $end
$var wire 1 0 A $end
$var wire 1 1 B $end
$var wire 1 ' Cin $end
$var wire 1 . Cout $end
$var wire 1 2 nA $end
$var wire 1 3 nB $end
$var wire 1 4 nCin $end
$var wire 1 5 o1 $end
$var wire 1 6 o2 $end
$var wire 1 7 o3 $end
$var wire 1 8 o4 $end
$var wire 1 9 o5 $end
$var wire 1 : o6 $end
$var wire 1 ; o7 $end
$var wire 1 < sum $end
$upscope $end
$scope module fa2 $end
$var wire 1 = A $end
$var wire 1 > B $end
$var wire 1 . Cin $end
$var wire 1 - Cout $end
$var wire 1 ? nA $end
$var wire 1 @ nB $end
$var wire 1 A nCin $end
$var wire 1 B o1 $end
$var wire 1 C o2 $end
$var wire 1 D o3 $end
$var wire 1 E o4 $end
$var wire 1 F o5 $end
$var wire 1 G o6 $end
$var wire 1 H o7 $end
$var wire 1 I sum $end
$upscope $end
$scope module fa3 $end
$var wire 1 J A $end
$var wire 1 K B $end
$var wire 1 - Cin $end
$var wire 1 , Cout $end
$var wire 1 L nA $end
$var wire 1 M nB $end
$var wire 1 N nCin $end
$var wire 1 O o1 $end
$var wire 1 P o2 $end
$var wire 1 Q o3 $end
$var wire 1 R o4 $end
$var wire 1 S o5 $end
$var wire 1 T o6 $end
$var wire 1 U o7 $end
$var wire 1 V sum $end
$upscope $end
$scope module fa4 $end
$var wire 1 W A $end
$var wire 1 X B $end
$var wire 1 , Cin $end
$var wire 1 + Cout $end
$var wire 1 Y nA $end
$var wire 1 Z nB $end
$var wire 1 [ nCin $end
$var wire 1 \ o1 $end
$var wire 1 ] o2 $end
$var wire 1 ^ o3 $end
$var wire 1 _ o4 $end
$var wire 1 ` o5 $end
$var wire 1 a o6 $end
$var wire 1 b o7 $end
$var wire 1 c sum $end
$upscope $end
$scope module fa5 $end
$var wire 1 d A $end
$var wire 1 e B $end
$var wire 1 + Cin $end
$var wire 1 * Cout $end
$var wire 1 f nA $end
$var wire 1 g nB $end
$var wire 1 h nCin $end
$var wire 1 i o1 $end
$var wire 1 j o2 $end
$var wire 1 k o3 $end
$var wire 1 l o4 $end
$var wire 1 m o5 $end
$var wire 1 n o6 $end
$var wire 1 o o7 $end
$var wire 1 p sum $end
$upscope $end
$scope module fa6 $end
$var wire 1 q A $end
$var wire 1 r B $end
$var wire 1 * Cin $end
$var wire 1 ) Cout $end
$var wire 1 s nA $end
$var wire 1 t nB $end
$var wire 1 u nCin $end
$var wire 1 v o1 $end
$var wire 1 w o2 $end
$var wire 1 x o3 $end
$var wire 1 y o4 $end
$var wire 1 z o5 $end
$var wire 1 { o6 $end
$var wire 1 | o7 $end
$var wire 1 } sum $end
$upscope $end
$scope module fa7 $end
$var wire 1 ~ A $end
$var wire 1 !" B $end
$var wire 1 ) Cin $end
$var wire 1 ( Cout $end
$var wire 1 "" nA $end
$var wire 1 #" nB $end
$var wire 1 $" nCin $end
$var wire 1 %" o1 $end
$var wire 1 &" o2 $end
$var wire 1 '" o3 $end
$var wire 1 (" o4 $end
$var wire 1 )" o5 $end
$var wire 1 *" o6 $end
$var wire 1 +" o7 $end
$var wire 1 ," sum $end
$upscope $end
$scope module fa8 $end
$var wire 1 -" A $end
$var wire 1 ." B $end
$var wire 1 ( Cin $end
$var wire 1 " Cout $end
$var wire 1 /" nA $end
$var wire 1 0" nB $end
$var wire 1 1" nCin $end
$var wire 1 2" o1 $end
$var wire 1 3" o2 $end
$var wire 1 4" o3 $end
$var wire 1 5" o4 $end
$var wire 1 6" o5 $end
$var wire 1 7" o6 $end
$var wire 1 8" o7 $end
$var wire 1 9" sum $end
$upscope $end
$upscope $end
$upscope $end
$enddefinitions $end
#0
$dumpvars
09"
08"
07"
06"
05"
04"
03"
02"
11"
10"
1/"
0."
0-"
0,"
0+"
0*"
0)"
0("
0'"
0&"
0%"
1$"
1#"
1""
0!"
0~
0}
0|
0{
0z
0y
0x
0w
0v
1u
1t
1s
0r
0q
0p
0o
0n
0m
0l
0k
0j
0i
1h
1g
1f
0e
0d
0c
0b
0a
0`
0_
0^
0]
0\
1[
1Z
1Y
0X
0W
0V
0U
0T
0S
0R
0Q
0P
0O
1N
1M
1L
0K
0J
0I
0H
0G
0F
0E
0D
0C
0B
1A
1@
1?
0>
0=
0<
0;
0:
09
08
07
06
05
14
13
12
01
00
b0 /
0.
0-
0,
0+
0*
0)
0(
0'
b0 &
b0 %
b0 $
b0 #
0"
b0 !
$end
#5
b1 !
b1 /
1<
16
02
10
b1 #
b1 %
#10
1I
1D
0A
b10 !
b10 /
0<
1.
06
1;
03
11
b1 $
b1 &
#20
1C
0V
1A
1<
0Q
1N
b11 !
b11 /
1I
0.
15
0-
0D
0;
12
0G
0?
00
1=
b10 #
b10 %
#30
1V
1Q
0N
0I
b100 !
b100 /
0<
1-
0C
05
13
1H
0@
01
1>
b10 $
b10 &
#40
b101 !
b101 /
1<
15
03
11
b11 $
b11 &
#50
1P
0c
1N
1I
0^
1[
b111 !
b111 /
1V
0-
1B
0,
0Q
0H
1?
0T
0L
0=
1J
b100 #
b100 %
#60
1c
1^
0[
0V
1,
0P
1T
0N
0I
1-
0B
1F
0A
b1000 !
b1000 /
0<
1.
05
1;
02
10
b101 #
b101 %
#70
1U
1A
1<
1N
0I
0.
16
0-
0D
b1001 !
b1001 /
0V
0T
0;
13
0F
1@
0R
0M
01
0>
1K
b100 $
b100 &
#80
1I
1D
0A
b1010 !
b1010 /
0<
1.
06
1;
03
11
b101 $
b101 &
#90
1C
0V
1U
1A
1<
0R
1N
b1011 !
b1011 /
1I
0.
15
0-
0D
0;
12
0G
0?
00
1=
b110 #
b110 %
#100
1V
0U
1R
0N
0I
b1100 !
b1100 /
0<
1-
0C
05
13
1H
0@
01
1>
b110 $
b110 &
#110
b1101 !
b1101 /
1<
16
02
10
b111 #
b111 %
#120
1I
0H
1E
0A
b1110 !
b1110 /
0<
1.
06
1;
03
11
b111 $
b111 &
#130
1]
1[
0,
1O
1N
0-
1B
0p
1A
1<
0k
1h
1c
0.
15
1I
0F
b1111 !
b1111 /
1V
0S
0+
0^
0;
12
0E
1?
0R
1L
0a
0Y
00
0=
0J
1W
b1000 #
b1000 %
#140
1p
1k
0h
0c
0<
0I
b10000 !
b10000 /
0V
1+
0]
05
13
0B
1@
0O
1M
1b
0Z
01
0>
0K
1X
b1000 $
b1000 &
#150
1}
1x
0u
0p
1I
b100110 !
b100110 /
1V
1*
0k
1C
0?
1P
0L
1n
0f
1=
1J
1d
b11110 #
b11110 %
#160
1c
0b
1R
0N
0I
1_
0[
1V
1-
0C
1,
0P
b111100 !
b111100 /
1p
0n
1H
0@
0U
0M
1l
0g
1>
1K
1e
b11110 $
b11110 &
