Assignment-4/G4R_200530_200562_200856_A4/A4Q1_graycode.v
// module declaration
module graycode(clk,count);

// port declaration
input clk;
output reg [2:0] count;

// state assignment
parameter S0=0,S1=1,S2=2,S3=3,S4=4,S5=5,S6=6,S7=7;
parameter X0=3'b000,X1=3'b001,X2=3'b011,X3=3'b010,X4=3'b110,X5=3'b111,X6=3'b101,X7=3'b100;
// here, Si is the state and Xi is the output associated with it
reg [2:0] state;

// state transitions to the next state
always @(posedge clk) begin
    case(state)
    S0:begin
        count<=X1;
        state<=S1;
    end
    S1:begin
        count<=X2;
        state<=S2;
    end
    S2:begin
        count<=X3;
        state<=S3;
    end
    S3:begin
        count<=X4;
        state<=S4;
    end
    S4:begin
        count<=X5;
        state<=S5;
    end
    S5:begin
        count<=X6;
        state<=S6;
    end
    S6:begin
        count<=X7;
        state<=S7;
    end
    S7:begin
        count<=X0;
        state<=S0;
    end
    default: begin   // by default start with S0
        count<=X0;
        state<=S0;
    end 
    endcase
end
endmodule

Assignment-4/G4R_200530_200562_200856_A4/A4Q1_graycode_tb.v
`timescale 1ns/1ns
`include "A4Q1_graycode.v"

module testbench;
reg clk;
wire [2:0] count;

graycode uut(clk,count);

always #5 clk=~clk;   // clock changes in 5 unit time

initial begin
    // initialising the clock
    clk=1'b0;
    #100 $finish;
end

initial begin
    // output
    $dumpfile("A4Q1_graycode_tb.vcd");
    $dumpvars(0,testbench);
    // counter works at the posedge of the clock
    $monitor("%0d count = %b", $time,count);
end

endmodule

Assignment-4/G4R_200530_200562_200856_A4/A4Q1_graycode_tb.vcd
$date
	Sun Mar 06 12:22:42 2022
$end
$version
	Icarus Verilog
$end
$timescale
	1ns
$end
$scope module testbench $end
$var wire 3 ! count [2:0] $end
$var reg 1 " clk $end
$scope module uut $end
$var wire 1 " clk $end
$var reg 3 # count [2:0] $end
$var reg 3 $ state [2:0] $end
$upscope $end
$upscope $end
$enddefinitions $end
#0
$dumpvars
bx $
bx #
0"
bx !
$end
#5
b0 $
b0 !
b0 #
1"
#10
0"
#15
b1 $
b1 !
b1 #
1"
#20
0"
#25
b10 $
b11 !
b11 #
1"
#30
0"
#35
b11 $
b10 !
b10 #
1"
#40
0"
#45
b100 $
b110 !
b110 #
1"
#50
0"
#55
b101 $
b111 !
b111 #
1"
#60
0"
#65
b110 $
b101 !
b101 #
1"
#70
0"
#75
b111 $
b100 !
b100 #
1"
#80
0"
#85
b0 $
b0 !
b0 #
1"
#90
0"
#95
b1 $
b1 !
b1 #
1"
